musubitraining/__init__.py
musubitraining/example.py
musubitraining/main.py
techtrash_musubitraining-0.0.11.dist-info/METADATA
techtrash_musubitraining-0.0.11.dist-info/WHEEL
techtrash_musubitraining-0.0.11.dist-info/licenses/LICENSE
techtrash_musubitraining-0.0.11.dist-info/RECORD
